<?xml version="1.0" encoding="UTF-8"?>

<!-- 
    HTTP 映射表.
 -->

<root type="HttpMappingPrototype">
    <httpMapping pid="200" name="IOS">
        <mapping msgId="1001" channel="http" uri="mgw/login" />
        <mapping msgId="1002" channel="http" uri="mgw/smsCode/send"/>
        <mapping msgId="1003" channel="http" uri="mgw/logout" />
        <mapping msgId="1004" channel="http" uri="mgw/categories" />
        <mapping msgId="1005" channel="http" uri="mgw/types" />
        <mapping msgId="1006" channel="http" uri="mgw/materials" />
        <mapping msgId="1007" channel="http" uri="mgw/innerDiameters" />
        <mapping msgId="1008" channel="http" uri="mgw/products" />
        <mapping msgId="1009" channel="http" uri="mgw/orders" dest="save order"/>
        <mapping msgId="1010" channel="http" uri="mgw/orders" dest="get orders"/>
        <mapping msgId="1012" channel="http" uri="mgw/versions?" dest="" />
        <mapping msgId="1013" channel="http" uri="mgw/products/listByMatch" dest="change" />
        <mapping msgId="1014" channel="http" uri="mgw/areas" dest="get areas" />
        <mapping msgId="1015" channel="http" uri="mgw/users/updateSelf" dest="update self" />
        <mapping msgId="1016" channel="http" uri="mgw/users/current" dest="login current user" />


        <mapping msgId="2001" channel="local" uri="mgw/login" />
        <mapping msgId="2002" channel="local" uri="mgw/smsCode/send"/>
        <mapping msgId="2003" channel="local" uri="mgw/logout"/>
        <mapping msgId="2004" channel="local" uri="mgw/categories" />
        <mapping msgId="2008" channel="local" uri="mgw/products" />
        <mapping msgId="2009" channel="local" uri="mgw/orders" />
        <mapping msgId="2010" channel="local" uri="mgw/orders" />
        <mapping msgId="2013" channel="local" uri="products/listByMatch" />
        <mapping msgId="2014" channel="local" uri="mgw/areas" dest="get areas" />
        <mapping msgId="2015" channel="local" uri="mgw/users/updateSelf" dest="update self" />
        <mapping msgId="2016" channel="local" uri="mgw/users/current" dest="login current user" />
        
        <mapping msgId="3001" channel="local" uri="" dest = "select actor send msg to UI"/>

    <httpMapping/>
</root>
